vel/__init__.py
vel/agent.py
vel/events.py
vel/core/__init__.py
vel/core/context.py
vel/core/file_output.py
vel/core/guardrails.py
vel/core/hooks.py
vel/core/json_stream_parser.py
vel/core/reducer.py
vel/core/structured_output.py
vel/core/tool_behavior.py
vel/memory/__init__.py
vel/memory/fact_store.py
vel/memory/strategy_reasoningbank.py
vel/prompts/__init__.py
vel/prompts/context_manager.py
vel/prompts/formatters.py
vel/prompts/manager.py
vel/prompts/registry.py
vel/prompts/template.py
vel/providers/__init__.py
vel/providers/anthropic.py
vel/providers/base.py
vel/providers/google.py
vel/providers/message_translator.py
vel/providers/openai.py
vel/providers/translators.py
vel/rlm/__init__.py
vel/rlm/budget.py
vel/rlm/config.py
vel/rlm/context_store.py
vel/rlm/controller.py
vel/rlm/prompts.py
vel/rlm/scratchpad.py
vel/rlm/tools.py
vel/rlm/utils.py
vel/thinking/__init__.py
vel/thinking/config.py
vel/thinking/controller.py
vel/thinking/prompts.py
vel/tools/__init__.py
vel/tools/registry.py
vel/tools/schema_generator.py
vel/utils/__init__.py
vel/utils/async_queue.py
vel/utils/message_converter.py
vel/utils/message_reducer.py
vel_ai-0.2.0.dist-info/METADATA
vel_ai-0.2.0.dist-info/WHEEL
vel_ai-0.2.0.dist-info/top_level.txt
vel_ai-0.2.0.dist-info/RECORD
