Metadata-Version: 2.4
Name: vel-ai
Version: 0.2.0
Summary: 12-Factor inspired AI agent runtime with streaming responses
Author: Richard Scheiwe
License-Expression: MIT
Project-URL: Homepage, https://github.com/rscheiwe/vel
Project-URL: Documentation, https://rscheiwe.github.io/vel
Project-URL: Repository, https://github.com/rscheiwe/vel
Project-URL: Issues, https://github.com/rscheiwe/vel/issues
Keywords: ai,agent,llm,openai,anthropic,gemini,streaming,12-factor
Classifier: Development Status :: 4 - Beta
Classifier: Intended Audience :: Developers
Classifier: Operating System :: OS Independent
Classifier: Programming Language :: Python :: 3
Classifier: Programming Language :: Python :: 3.10
Classifier: Programming Language :: Python :: 3.11
Classifier: Programming Language :: Python :: 3.12
Classifier: Topic :: Scientific/Engineering :: Artificial Intelligence
Classifier: Topic :: Software Development :: Libraries :: Python Modules
Classifier: Typing :: Typed
Requires-Python: >=3.10
Requires-Dist: httpx>=0.27.0
Requires-Dist: anyio>=4.4.0
Requires-Dist: pydantic>=2.8.0
Requires-Dist: jsonschema>=4.22.0
Requires-Dist: python-dotenv>=1.0.1
Requires-Dist: tenacity>=8.2.3
Requires-Dist: jinja2>=3.1.0
Requires-Dist: openai>=1.54.0
Requires-Dist: google-generativeai>=0.8.0
Requires-Dist: anthropic>=0.39.0
Provides-Extra: dev
Requires-Dist: pytest>=8.3.2; extra == "dev"
Requires-Dist: pytest-asyncio>=0.23.7; extra == "dev"
Requires-Dist: ruff>=0.6.9; extra == "dev"
Requires-Dist: black>=24.8.0; extra == "dev"
Requires-Dist: mypy>=1.11.0; extra == "dev"
